anthon.py
anthon-0.0.1.dist-info/WHEEL
anthon-0.0.1.dist-info/METADATA
anthon-0.0.1.dist-info/RECORD
