Metadata-Version: 2.1
Name: anthon
Version: 0.0.1
Summary: Just trying flit here 
Home-page: UNKNOWN
License: UNKNOWN
Author: Rizaldi Martaputra
Author-email: rizaldi.m@bridestory.com
Classifier: License :: OSI Approved :: MIT License
